mylibadadafahabzkjabxljwxbclwcbnpi/__inint__.py
mylibadadafahabzkjabxljwxbclwcbnpi/example.py
mylibadadafahabzkjabxljwxbclwcbnpi-0.5.dist-info/LICENSE
mylibadadafahabzkjabxljwxbclwcbnpi-0.5.dist-info/METADATA
mylibadadafahabzkjabxljwxbclwcbnpi-0.5.dist-info/WHEEL
mylibadadafahabzkjabxljwxbclwcbnpi-0.5.dist-info/top_level.txt
mylibadadafahabzkjabxljwxbclwcbnpi-0.5.dist-info/RECORD
